edgify/__init__.py
edgify/version.py
edgify/models/__init__.py
edgify/models/mnist_classifier.py
edgify/utils/__init__.py
edgify/utils/qmnist_writer_dataset.py
edgify-0.0.1.dist-info/LICENSE
edgify-0.0.1.dist-info/METADATA
edgify-0.0.1.dist-info/WHEEL
edgify-0.0.1.dist-info/top_level.txt
edgify-0.0.1.dist-info/RECORD
