Metadata-Version: 2.1
Name: edgify
Version: 0.0.1
Summary: Personalize DL models on the edge.
Home-page: https://github.com/scale-lab/edgify
Author: Abdelrahman Hosny
Author-email: abdelrahman_hosny@brown.edu
License: BSD-3 License
Download-URL: https://github.com/scale-lab/archive/v_0.0.1.tar.gz
Keywords: Edge,Computing,Deep Learning
Platform: UNKNOWN
Classifier: Development Status :: 3 - Alpha
Classifier: Intended Audience :: Developers
Classifier: Topic :: Scientific/Engineering :: Artificial Intelligence
Classifier: License :: OSI Approved :: BSD License
Classifier: Programming Language :: Python :: 3
Classifier: Programming Language :: Python :: 3.4
Classifier: Programming Language :: Python :: 3.5
Classifier: Programming Language :: Python :: 3.6
Requires-Dist: torch (==1.6.0)
Requires-Dist: torchvision (==0.7.0)
